validador_datos/__init__.py
validador_datos/cli.py
validador_datos/email.py
validador_datos/exceptions.py
validador_datos/password.py
validador_datos-0.1.0.dist-info/METADATA
validador_datos-0.1.0.dist-info/WHEEL
validador_datos-0.1.0.dist-info/top_level.txt
validador_datos-0.1.0.dist-info/RECORD
