Metadata-Version: 2.4
Name: validador-datos
Version: 0.1.0
Summary: Paquete para validar emails y passwords
Home-page: https://tusitio-o-repositorio-aqui
Author: DogTheRc
Author-email: skipper@a.com
Classifier: Programming Language :: Python :: 3
Classifier: License :: OSI Approved :: MIT License
Classifier: Operating System :: OS Independent
Requires-Python: >=3.10
Requires-Dist: regex
Dynamic: author
Dynamic: author-email
Dynamic: classifier
Dynamic: description
Dynamic: description-content-type
Dynamic: home-page
Dynamic: requires-dist
Dynamic: requires-python
Dynamic: summary
